LICENSE.txt
MANIFEST.in
Makefile
README.md
align.c
bseq.c
bseq.h
esterr.c
format.c
hit.c
index.c
jump.c
kalloc.c
kalloc.h
kdq.h
ketopt.h
khash.h
krmq.h
kseq.h
ksort.h
ksw2.h
ksw2_dispatch.c
ksw2_extd2_sse.c
ksw2_exts2_sse.c
ksw2_extz2_sse.c
ksw2_ll_sse.c
kthread.c
kthread.h
kvec.h
lchain.c
main.c
map.c
minimap.h
misc.c
mmpriv.h
options.c
pe.c
pyproject.toml
sdust.c
sdust.h
seed.c
setup.py
sketch.c
splitidx.c
mappy.egg-info/PKG-INFO
mappy.egg-info/SOURCES.txt
mappy.egg-info/dependency_links.txt
mappy.egg-info/top_level.txt
python/README.rst
python/cmappy.h
python/cmappy.pxd
python/mappy.pyx
python/minimap2.py
sse2neon/emmintrin.h